dicom2nifti/__init__.py
dicom2nifti/common.py
dicom2nifti/convert_dicom.py
dicom2nifti/convert_dir.py
dicom2nifti/convert_ge.py
dicom2nifti/convert_generic.py
dicom2nifti/convert_hitachi.py
dicom2nifti/convert_philips.py
dicom2nifti/convert_siemens.py
dicom2nifti/exceptions.py
dicom2nifti/image_reorientation.py
dicom2nifti/image_volume.py
dicom2nifti/patch_pydicom_encodings.py
dicom2nifti/resample.py
dicom2nifti/settings.py
dicom2nifti-2.6.1.data/scripts/dicom2nifti
dicom2nifti-2.6.1.dist-info/licenses/LICENSE
dicom2nifti-2.6.1.dist-info/METADATA
dicom2nifti-2.6.1.dist-info/WHEEL
dicom2nifti-2.6.1.dist-info/top_level.txt
dicom2nifti-2.6.1.dist-info/RECORD
