Metadata-Version: 2.4
Name: dicom2nifti
Version: 2.6.1
Summary: package for converting dicom files to nifti
Home-page: https://github.com/icometrix/dicom2nifti
Download-URL: https://github.com/icometrix/dicom2nifti/tarball/2.6.1
Author: icometrix NV
Author-email: dicom2nifti@icometrix.com
Maintainer: icometrix NV
Maintainer-email: dicom2nifti@icometrix.com
License: MIT
Keywords: dicom,nifti,medical imaging
Classifier: Development Status :: 5 - Production/Stable
Classifier: Intended Audience :: Healthcare Industry
Classifier: Intended Audience :: Science/Research
Classifier: Topic :: Scientific/Engineering :: Medical Science Apps.
Classifier: Programming Language :: Python :: 3
Classifier: Programming Language :: Python :: 3.10
Classifier: Programming Language :: Python :: 3.11
Classifier: Programming Language :: Python :: 3.12
Classifier: Operating System :: MacOS :: MacOS X
Classifier: Operating System :: POSIX :: Linux
License-File: LICENSE
Requires-Dist: nibabel
Requires-Dist: numpy
Requires-Dist: scipy
Requires-Dist: pydicom>=3.0.0
Requires-Dist: python-gdcm
Dynamic: author
Dynamic: author-email
Dynamic: classifier
Dynamic: description
Dynamic: download-url
Dynamic: home-page
Dynamic: keywords
Dynamic: license
Dynamic: license-file
Dynamic: maintainer
Dynamic: maintainer-email
Dynamic: requires-dist
Dynamic: summary
